matrix/__init__.py
matrix/__main__.py
matrix/cli.py
matrix/matrix_server.py
matrix/agents/README.md
matrix/agents/agent_utils.py
matrix/agents/p2p_agents.py
matrix/agents/p2p_extended.py
matrix/agents/config/coral_mmlu_pro.yaml
matrix/agents/config/mini_swe_agent.yaml
matrix/agents/config/nr_curation.yaml
matrix/agents/config/simulation.yaml
matrix/agents/config/tau2_bench.yaml
matrix/agents/config/agents/coral_agents.yaml
matrix/agents/config/agents/nr_agents.yaml
matrix/agents/config/agents/sink.yaml
matrix/agents/config/agents/swe_agents.yaml
matrix/agents/config/agents/tau2_agents.yaml
matrix/agents/config/containers/tau2_bench.def
matrix/agents/config/dataset/coral_dataset.yaml
matrix/agents/config/dataset/nr_dataset.yaml
matrix/agents/config/dataset/swe_dataset.yaml
matrix/agents/config/dataset/tau2_dataset.yaml
matrix/agents/config/metrics/coral_metrics.yaml
matrix/agents/config/metrics/nr_metrics.yaml
matrix/agents/config/metrics/swe_metrics.yaml
matrix/agents/config/metrics/tau2_metrics.yaml
matrix/agents/config/orchestrator/coral_sequential.yaml
matrix/agents/config/orchestrator/nr_sequential.yaml
matrix/agents/config/orchestrator/swe_orchestrator.yaml
matrix/agents/config/orchestrator/tau2_orchestrator.yaml
matrix/agents/config/resources/coral_resources.yaml
matrix/agents/config/resources/nr_resources.yaml
matrix/agents/config/resources/swe_resources.yaml
matrix/agents/config/resources/tau2_resources.yaml
matrix/agents/examples/mini_swe_agent.py
matrix/agents/examples/nr_curation.py
matrix/agents/examples/tau2_bench.py
matrix/agents/examples/ts_interaction.py
matrix/agents/scripts/convert_swebench_to_apptainer.py
matrix/agents/scripts/nr_baseline.py
matrix/app_server/__init__.py
matrix/app_server/app_api.py
matrix/app_server/deploy_utils.py
matrix/app_server/code/__init__.py
matrix/app_server/code/code_execution_app.py
matrix/app_server/code/sandbox_runner.py
matrix/app_server/container/container_deployment.py
matrix/app_server/hello/__init__.py
fair_matrix-0.2.5.dist-info/entry_points.txt
fair_matrix-0.2.5.dist-info/licenses/LICENSE
fair_matrix-0.2.5.dist-info/WHEEL
fair_matrix-0.2.5.dist-info/METADATA
fair_matrix-0.2.5.dist-info/RECORD
