Metadata-Version: 2.4
Name: fair-matrix
Version: 0.2.5
Summary: matrix.
Author: Facebook AI Research
Requires-Python: >=3.10
Classifier: License :: OSI Approved :: MIT License
Classifier: Topic :: Scientific/Engineering
Classifier: Development Status :: 4 - Beta
License-File: LICENSE
Requires-Dist: psutil
Requires-Dist: datasets
Requires-Dist: grpcio==1.70.0
Requires-Dist: grpcio-tools==1.70.0
Requires-Dist: fire
Requires-Dist: jinja2
Requires-Dist: pyyaml
Requires-Dist: portalocker
Requires-Dist: aiohttp~=3.12
Requires-Dist: requests~=2.32
Requires-Dist: httpx~=0.28
Requires-Dist: openai~=1.90
Requires-Dist: hydra-core
Requires-Dist: zstandard
Requires-Dist: pytest>=4.3.0 ; extra == "dev"
Requires-Dist: pytest-asyncio>=0.26.0 ; extra == "dev"
Requires-Dist: coverage[toml]>=5.1 ; extra == "dev"
Requires-Dist: black==24.10.0 ; extra == "dev"
Requires-Dist: isort>=5.12.0 ; extra == "dev"
Requires-Dist: pre-commit ; extra == "dev"
Requires-Dist: mypy>=1.13.0 ; extra == "dev"
Requires-Dist: pylint>=2.8.0 ; extra == "dev"
Requires-Dist: types-PyYAML ; extra == "dev"
Requires-Dist: types-requests ; extra == "dev"
Requires-Dist: flit>=3.5.1 ; extra == "dev"
Requires-Dist: sphinx ; extra == "dev"
Requires-Dist: furo ; extra == "dev"
Requires-Dist: myst-parser ; extra == "dev"
Requires-Dist: sphinx-autodoc-typehints ; extra == "dev"
Requires-Dist: ghp-import ; extra == "dev"
Requires-Dist: submitit>=1.5.2 ; extra == "sglang-045"
Requires-Dist: transformers>=4.45.2 ; extra == "sglang-045"
Requires-Dist: torch>=2.5.1 ; extra == "sglang-045"
Requires-Dist: sglang[all]==0.4.5.post1 ; extra == "sglang-045"
Requires-Dist: sglang-router ; extra == "sglang-045"
Requires-Dist: boto3 ; extra == "sglang-045"
Requires-Dist: google-genai>=1.13.0 ; extra == "sglang-045"
Requires-Dist: datasketch ; extra == "sglang-045"
Requires-Dist: s3fs ; extra == "sglang-045"
Requires-Dist: datasets ; extra == "sglang-045"
Requires-Dist: iopath ; extra == "sglang-045"
Requires-Dist: jsonlines ; extra == "sglang-045"
Requires-Dist: submitit>=1.5.2 ; extra == "vision"
Requires-Dist: transformers>=4.45.2 ; extra == "vision"
Requires-Dist: vllm==v0.8.3 ; extra == "vision"
Requires-Dist: ray[serve]==2.43.0 ; extra == "vision"
Requires-Dist: torch>=2.6.0 ; extra == "vision"
Requires-Dist: boto3 ; extra == "vision"
Requires-Dist: google-genai>=1.13.0 ; extra == "vision"
Requires-Dist: datasketch ; extra == "vision"
Requires-Dist: s3fs ; extra == "vision"
Requires-Dist: datasets ; extra == "vision"
Requires-Dist: iopath ; extra == "vision"
Requires-Dist: jsonlines ; extra == "vision"
Requires-Dist: opencv-python ; extra == "vision"
Requires-Dist: tenacity ; extra == "vision"
Requires-Dist: submitit>=1.5.2 ; extra == "vllm-0102"
Requires-Dist: transformers>=4.45.2 ; extra == "vllm-0102"
Requires-Dist: torch>=2.7.1 ; extra == "vllm-0102"
Requires-Dist: vllm==0.10.2 ; extra == "vllm-0102"
Requires-Dist: ray[serve]>=2.48.0 ; extra == "vllm-0102"
Requires-Dist: boto3 ; extra == "vllm-0102"
Requires-Dist: google-genai>=1.13.0 ; extra == "vllm-0102"
Requires-Dist: datasketch ; extra == "vllm-0102"
Requires-Dist: s3fs ; extra == "vllm-0102"
Requires-Dist: datasets ; extra == "vllm-0102"
Requires-Dist: iopath ; extra == "vllm-0102"
Requires-Dist: jsonlines ; extra == "vllm-0102"
Requires-Dist: submitit>=1.5.2 ; extra == "vllm-0112"
Requires-Dist: transformers>=4.57.3 ; extra == "vllm-0112"
Requires-Dist: torch>=2.7.1 ; extra == "vllm-0112"
Requires-Dist: vllm==0.11.2 ; extra == "vllm-0112"
Requires-Dist: ray[serve]>=2.48.0 ; extra == "vllm-0112"
Requires-Dist: boto3 ; extra == "vllm-0112"
Requires-Dist: google-genai>=1.13.0 ; extra == "vllm-0112"
Requires-Dist: datasketch ; extra == "vllm-0112"
Requires-Dist: s3fs ; extra == "vllm-0112"
Requires-Dist: datasets ; extra == "vllm-0112"
Requires-Dist: iopath ; extra == "vllm-0112"
Requires-Dist: jsonlines ; extra == "vllm-0112"
Requires-Dist: submitit>=1.5.2 ; extra == "vllm-066"
Requires-Dist: transformers>=4.45.2 ; extra == "vllm-066"
Requires-Dist: torch>=2.5.1 ; extra == "vllm-066"
Requires-Dist: vllm==v0.6.6.post1 ; extra == "vllm-066"
Requires-Dist: ray[serve]==2.40.0 ; extra == "vllm-066"
Requires-Dist: boto3 ; extra == "vllm-066"
Requires-Dist: google-genai>=1.13.0 ; extra == "vllm-066"
Requires-Dist: datasketch ; extra == "vllm-066"
Requires-Dist: s3fs ; extra == "vllm-066"
Requires-Dist: datasets ; extra == "vllm-066"
Requires-Dist: iopath ; extra == "vllm-066"
Requires-Dist: jsonlines ; extra == "vllm-066"
Requires-Dist: submitit>=1.5.2 ; extra == "vllm-073"
Requires-Dist: transformers>=4.45.2 ; extra == "vllm-073"
Requires-Dist: torch>=2.5.1 ; extra == "vllm-073"
Requires-Dist: vllm==v0.7.3 ; extra == "vllm-073"
Requires-Dist: ray[serve]==2.40.0 ; extra == "vllm-073"
Requires-Dist: boto3 ; extra == "vllm-073"
Requires-Dist: google-genai>=1.13.0 ; extra == "vllm-073"
Requires-Dist: datasketch ; extra == "vllm-073"
Requires-Dist: s3fs ; extra == "vllm-073"
Requires-Dist: datasets ; extra == "vllm-073"
Requires-Dist: iopath ; extra == "vllm-073"
Requires-Dist: jsonlines ; extra == "vllm-073"
Requires-Dist: submitit>=1.5.2 ; extra == "vllm-083"
Requires-Dist: transformers>=4.45.2 ; extra == "vllm-083"
Requires-Dist: vllm==v0.8.3 ; extra == "vllm-083"
Requires-Dist: ray[serve]==2.43.0 ; extra == "vllm-083"
Requires-Dist: torch>=2.6.0 ; extra == "vllm-083"
Requires-Dist: boto3 ; extra == "vllm-083"
Requires-Dist: google-genai>=1.13.0 ; extra == "vllm-083"
Requires-Dist: datasketch ; extra == "vllm-083"
Requires-Dist: s3fs ; extra == "vllm-083"
Requires-Dist: datasets ; extra == "vllm-083"
Requires-Dist: iopath ; extra == "vllm-083"
Requires-Dist: jsonlines ; extra == "vllm-083"
Requires-Dist: submitit>=1.5.2 ; extra == "vllm-085"
Requires-Dist: transformers>=4.45.2 ; extra == "vllm-085"
Requires-Dist: torch>=2.6.0 ; extra == "vllm-085"
Requires-Dist: vllm==v0.8.5.post1 ; extra == "vllm-085"
Requires-Dist: ray[serve]==2.46.0 ; extra == "vllm-085"
Requires-Dist: boto3 ; extra == "vllm-085"
Requires-Dist: google-genai>=1.13.0 ; extra == "vllm-085"
Requires-Dist: datasketch ; extra == "vllm-085"
Requires-Dist: s3fs ; extra == "vllm-085"
Requires-Dist: datasets ; extra == "vllm-085"
Requires-Dist: iopath ; extra == "vllm-085"
Requires-Dist: jsonlines ; extra == "vllm-085"
Project-URL: Source, https://github.com/facebookresearch/matrix
Project-URL: Tracker, https://github.com/facebookresearch/matrix/issues
Provides-Extra: dev
Provides-Extra: sglang-045
Provides-Extra: vision
Provides-Extra: vllm-0102
Provides-Extra: vllm-0112
Provides-Extra: vllm-066
Provides-Extra: vllm-073
Provides-Extra: vllm-083
Provides-Extra: vllm-085
